.gitignore
.pylintrc
LICENSE
MANIFEST.in
README.md
__init__.py
build.sh
bump_version.sh
download_tortoise_voices.sh
optional-requirements.txt
pyproject.toml
quickstart.ps1
quickstart.sh
real_build.sh
requirements.txt
version
examples/voices/tortoise/adam.mp3
examples/voices/tortoise/angie.mp3
examples/voices/tortoise/applejack.mp3
examples/voices/tortoise/cond_latent_example.mp3
examples/voices/tortoise/daniel.mp3
examples/voices/tortoise/deniro.mp3
examples/voices/tortoise/emma.mp3
examples/voices/tortoise/freeman.mp3
examples/voices/tortoise/geralt.mp3
examples/voices/tortoise/halle.mp3
examples/voices/tortoise/jlaw.mp3
examples/voices/tortoise/lj.mp3
examples/voices/tortoise/mol.mp3
examples/voices/tortoise/myself.mp3
examples/voices/tortoise/pat.mp3
examples/voices/tortoise/pat2.mp3
examples/voices/tortoise/rainbow.mp3
examples/voices/tortoise/reader.mp3
examples/voices/tortoise/snakes.mp3
examples/voices/tortoise/tim_reynolds.mp3
examples/voices/tortoise/tom.mp3
examples/voices/tortoise/train_atkins.mp3
examples/voices/tortoise/train_daws.mp3
examples/voices/tortoise/train_dotrice.mp3
examples/voices/tortoise/train_dreams.mp3
examples/voices/tortoise/train_empire.mp3
examples/voices/tortoise/train_grace.mp3
examples/voices/tortoise/train_kennard.mp3
examples/voices/tortoise/train_lescault.mp3
examples/voices/tortoise/train_mouse.mp3
examples/voices/tortoise/weaver.mp3
examples/voices/tortoise/william.mp3
examples/voices/xtts/aaron-dreschner.mp3
examples/voices/xtts/abrahan-mack.mp3
examples/voices/xtts/adde-michal.mp3
examples/voices/xtts/alexandra-hisakawa.mp3
examples/voices/xtts/alison-dietlinde.mp3
examples/voices/xtts/alma-maria.mp3
examples/voices/xtts/ana-florence.mp3
examples/voices/xtts/andrew-chipper.mp3
examples/voices/xtts/annmarie-nele.mp3
examples/voices/xtts/asya-anara.mp3
examples/voices/xtts/badr-odhiambo.mp3
examples/voices/xtts/baldur-sanjin.mp3
examples/voices/xtts/barbora-maclean.mp3
examples/voices/xtts/brenda-stern.mp3
src/ttspod.egg-info/PKG-INFO
src/ttspod.egg-info/SOURCES.txt
src/ttspod.egg-info/dependency_links.txt
src/ttspod.egg-info/entry_points.txt
src/ttspod.egg-info/requires.txt
src/ttspod.egg-info/top_level.txt
