Metadata-Version: 2.1
Name: ttspod
Version: 0.1.436
Summary: Convert any content to a podcast
Author-email: Adam Kessel <adam@rosi-kessel.org>
Maintainer-email: Adam Kessel <adam@rosi-kessel.org>
License: MIT License
Project-URL: Homepage, https://github.com/ajkessel/ttspod
Project-URL: Documentation, https://github.com/ajkessel/ttspod/blob/main/README.md
Project-URL: Repository, https://github.com/ajkessel/ttspod
Project-URL: Issues, https://github.com/ajkessel/ttspod/issues
Project-URL: Changelog, https://github.com/ajkessel/ttspod/commits/main/
Keywords: podcast,text-to-speech
Classifier: Development Status :: 3 - Alpha
Classifier: Intended Audience :: End Users/Desktop
Classifier: License :: OSI Approved :: MIT License
Classifier: Programming Language :: Python :: 3.11
Classifier: Operating System :: POSIX :: Linux
Classifier: Operating System :: MacOS :: MacOS X
Classifier: Environment :: MacOS X
Classifier: Environment :: Win32 (MS Windows)
Requires-Python: ==3.11.*
License-File: LICENSE
Requires-Dist: anyascii
Requires-Dist: cython
Requires-Dist: fastapi
Requires-Dist: Requests
Requires-Dist: Unidecode
Requires-Dist: ffmpeg
Requires-Dist: html2text
Requires-Dist: instapaper
Requires-Dist: ipython
Requires-Dist: lxml
Requires-Dist: lxml_html_clean
Requires-Dist: nltk
Requires-Dist: numpy<=1.26.4
Requires-Dist: pandoc
Requires-Dist: paramiko
Requires-Dist: pip
Requires-Dist: pocket
Requires-Dist: pocket_api
Requires-Dist: pod2gen
Requires-Dist: posix_ipc; platform_system != "Windows"
Requires-Dist: psutil
Requires-Dist: python-magic-bin; platform_system == "Windows"
Requires-Dist: semaphore_win_ctypes; platform_system == "Windows"
Requires-Dist: spacy<3.8,>=3
Requires-Dist: pydub
Requires-Dist: pyenchant
Requires-Dist: pymupdf
Requires-Dist: pypandoc
Requires-Dist: pypandoc-binary
Requires-Dist: python-dotenv
Requires-Dist: python_magic; platform_system != "Windows"
Requires-Dist: trafilatura
Requires-Dist: validators
Provides-Extra: local
Requires-Dist: torch>=2.2.2; extra == "local"
Requires-Dist: torchaudio>=2.2.2; extra == "local"
Requires-Dist: whisperspeech; extra == "local"
Requires-Dist: webdataset; extra == "local"
Requires-Dist: coqui-tts==0.24.3; extra == "local"
Requires-Dist: transformers; extra == "local"
Requires-Dist: coqui-tts-trainer; extra == "local"
Requires-Dist: ctranslate2; extra == "local"
Provides-Extra: remote
Requires-Dist: openai; extra == "remote"
Requires-Dist: elevenlabs; extra == "remote"
Provides-Extra: truststore
Requires-Dist: truststore; extra == "truststore"
Provides-Extra: dev
Requires-Dist: posix_ipc; platform_system != "Windows" and extra == "dev"
Requires-Dist: semaphore_win_ctypes; extra == "dev"
Requires-Dist: build; extra == "dev"
Requires-Dist: twine; extra == "dev"
